slugkit/__init__.py
slugkit/async_client.py
slugkit/base.py
slugkit/cli.py
slugkit/errors.py
slugkit/package_data.py
slugkit/sync_client.py
slugkit/data/dictionary-and-tag-reference.md
slugkit/data/pattern-examples.md
slugkit/data/pattern-grammar.ebnf
slugkit/data/pattern-syntax-reference.md
slugkit/data/quick-start-guilde.md
slugkit/mcp/__init__.py
slugkit/mcp/server.py
slugkit_py_sdk-0.0.4.dist-info/METADATA
slugkit_py_sdk-0.0.4.dist-info/WHEEL
slugkit_py_sdk-0.0.4.dist-info/entry_points.txt
slugkit_py_sdk-0.0.4.dist-info/licenses/LICENSE
slugkit_py_sdk-0.0.4.dist-info/RECORD
