Metadata-Version: 2.4
Name: slugkit-py-sdk
Version: 0.0.4
Summary: SlugKit Python SDK
Project-URL: Homepage, https://dev.slugkit.dev
Project-URL: Issues, https://github.com/slugkit/slugkit-py-sdk/issues
Project-URL: Source, https://github.com/slugkit/slugkit-py-sdk
Author-email: Sergei Fedorov <sergei@slugkit.dev>
License-Expression: MIT
License-File: LICENSE
Classifier: Development Status :: 4 - Beta
Classifier: Intended Audience :: Developers
Classifier: License :: OSI Approved :: MIT License
Classifier: Operating System :: OS Independent
Classifier: Programming Language :: Python :: 3
Classifier: Programming Language :: Python :: 3.11
Requires-Python: >=3.11
Requires-Dist: httpx>=0.28.1
Requires-Dist: mcp>=1.6.0
Requires-Dist: pydantic>=2.7.0
Requires-Dist: python-dotenv>=1.0.1
Requires-Dist: typer>=0.16.0
